{"nodes": [{"id": "c_tt_ai_stack_01_projects_makeover_talent_agency_services_market_scout_scraper_main_py", "label": "main.py", "file_type": "code", "source_file": "services/market-scout/scraper/main.py", "source_location": "L1"}, {"id": "scraper_main_ai_enabled", "label": "ai_enabled()", "file_type": "code", "source_file": "services/market-scout/scraper/main.py", "source_location": "L22"}, {"id": "scraper_main_main", "label": "main()", "file_type": "code", "source_file": "services/market-scout/scraper/main.py", "source_location": "L25"}], "edges": [{"source": "c_tt_ai_stack_01_projects_makeover_talent_agency_services_market_scout_scraper_main_py", "target": "os", "relation": "imports", "context": "import", "confidence": "EXTRACTED", "source_file": "services/market-scout/scraper/main.py", "source_location": "L1", "weight": 1.0}, {"source": "c_tt_ai_stack_01_projects_makeover_talent_agency_services_market_scout_scraper_main_py", "target": "sys", "relation": "imports", "context": "import", "confidence": "EXTRACTED", "source_file": "services/market-scout/scraper/main.py", "source_location": "L2", "weight": 1.0}, {"source": "c_tt_ai_stack_01_projects_makeover_talent_agency_services_market_scout_scraper_main_py", "target": "yaml", "relation": "imports", "context": "import", "confidence": "EXTRACTED", "source_file": "services/market-scout/scraper/main.py", "source_location": "L3", "weight": 1.0}, {"source": "c_tt_ai_stack_01_projects_makeover_talent_agency_services_market_scout_scraper_main_py", "target": "pathlib", "relation": "imports_from", "context": "import", "confidence": "EXTRACTED", "source_file": "services/market-scout/scraper/main.py", "source_location": "L4", "weight": 1.0}, {"source": "c_tt_ai_stack_01_projects_makeover_talent_agency_services_market_scout_scraper_main_py", "target": "dotenv", "relation": "imports_from", "context": "import", "confidence": "EXTRACTED", "source_file": "services/market-scout/scraper/main.py", "source_location": "L5", "weight": 1.0}, {"source": "c_tt_ai_stack_01_projects_makeover_talent_agency_services_market_scout_scraper_main_py", "target": "scraper_sources", "relation": "imports_from", "context": "import", "confidence": "EXTRACTED", "source_file": "services/market-scout/scraper/main.py", "source_location": "L14", "weight": 1.0}, {"source": "c_tt_ai_stack_01_projects_makeover_talent_agency_services_market_scout_scraper_main_py", "target": "storage_supabase_sync", "relation": "imports_from", "context": "import", "confidence": "EXTRACTED", "source_file": "services/market-scout/scraper/main.py", "source_location": "L15", "weight": 1.0}, {"source": "c_tt_ai_stack_01_projects_makeover_talent_agency_services_market_scout_scraper_main_py", "target": "scraper_main_ai_enabled", "relation": "contains", "confidence": "EXTRACTED", "source_file": "services/market-scout/scraper/main.py", "source_location": "L22", "weight": 1.0}, {"source": "c_tt_ai_stack_01_projects_makeover_talent_agency_services_market_scout_scraper_main_py", "target": "scraper_main_main", "relation": "contains", "confidence": "EXTRACTED", "source_file": "services/market-scout/scraper/main.py", "source_location": "L25", "weight": 1.0}, {"source": "scraper_main_main", "target": "scraper_main_ai_enabled", "relation": "calls", "context": "call", "confidence": "EXTRACTED", "source_file": "services/market-scout/scraper/main.py", "source_location": "L59", "weight": 1.0}], "raw_calls": [{"caller_nid": "scraper_main_ai_enabled", "callee": "get", "is_member_call": true, "source_file": "C:\\tt-ai-stack\\01_projects\\makeover-talent-agency\\services\\market-scout\\scraper\\main.py", "source_location": "L23", "receiver": null}, {"caller_nid": "scraper_main_main", "callee": "exists", "is_member_call": true, "source_file": "C:\\tt-ai-stack\\01_projects\\makeover-talent-agency\\services\\market-scout\\scraper\\main.py", "source_location": "L30", "receiver": "config_path"}, {"caller_nid": "scraper_main_main", "callee": "safe_load", "is_member_call": true, "source_file": "C:\\tt-ai-stack\\01_projects\\makeover-talent-agency\\services\\market-scout\\scraper\\main.py", "source_location": "L33", "receiver": "yaml"}, {"caller_nid": "scraper_main_main", "callee": "read_text", "is_member_call": true, "source_file": "C:\\tt-ai-stack\\01_projects\\makeover-talent-agency\\services\\market-scout\\scraper\\main.py", "source_location": "L33", "receiver": "config_path"}, {"caller_nid": "scraper_main_main", "callee": "fetch_fn", "is_member_call": false, "source_file": "C:\\tt-ai-stack\\01_projects\\makeover-talent-agency\\services\\market-scout\\scraper\\main.py", "source_location": "L39", "receiver": null}, {"caller_nid": "scraper_main_main", "callee": "extend", "is_member_call": true, "source_file": "C:\\tt-ai-stack\\01_projects\\makeover-talent-agency\\services\\market-scout\\scraper\\main.py", "source_location": "L41", "receiver": "all_items"}, {"caller_nid": "scraper_main_main", "callee": "get", "is_member_call": true, "source_file": "C:\\tt-ai-stack\\01_projects\\makeover-talent-agency\\services\\market-scout\\scraper\\main.py", "source_location": "L48", "receiver": "item"}, {"caller_nid": "scraper_main_main", "callee": "add", "is_member_call": true, "source_file": "C:\\tt-ai-stack\\01_projects\\makeover-talent-agency\\services\\market-scout\\scraper\\main.py", "source_location": "L49", "receiver": "seen"}, {"caller_nid": "scraper_main_main", "callee": "append", "is_member_call": true, "source_file": "C:\\tt-ai-stack\\01_projects\\makeover-talent-agency\\services\\market-scout\\scraper\\main.py", "source_location": "L50", "receiver": "deduped"}, {"caller_nid": "scraper_main_main", "callee": "read_text", "is_member_call": true, "source_file": "C:\\tt-ai-stack\\01_projects\\makeover-talent-agency\\services\\market-scout\\scraper\\main.py", "source_location": "L63", "receiver": "context_path"}, {"caller_nid": "scraper_main_main", "callee": "exists", "is_member_call": true, "source_file": "C:\\tt-ai-stack\\01_projects\\makeover-talent-agency\\services\\market-scout\\scraper\\main.py", "source_location": "L63", "receiver": "context_path"}, {"caller_nid": "scraper_main_main", "callee": "analyse_batch", "is_member_call": false, "source_file": "C:\\tt-ai-stack\\01_projects\\makeover-talent-agency\\services\\market-scout\\scraper\\main.py", "source_location": "L66", "receiver": null}, {"caller_nid": "scraper_main_main", "callee": "get", "is_member_call": true, "source_file": "C:\\tt-ai-stack\\01_projects\\makeover-talent-agency\\services\\market-scout\\scraper\\main.py", "source_location": "L72", "receiver": null}, {"caller_nid": "scraper_main_main", "callee": "get", "is_member_call": true, "source_file": "C:\\tt-ai-stack\\01_projects\\makeover-talent-agency\\services\\market-scout\\scraper\\main.py", "source_location": "L72", "receiver": "config"}, {"caller_nid": "scraper_main_main", "callee": "sync", "is_member_call": false, "source_file": "C:\\tt-ai-stack\\01_projects\\makeover-talent-agency\\services\\market-scout\\scraper\\main.py", "source_location": "L76", "receiver": null}, {"caller_nid": "scraper_main_main", "callee": "get_client", "is_member_call": false, "source_file": "C:\\tt-ai-stack\\01_projects\\makeover-talent-agency\\services\\market-scout\\scraper\\main.py", "source_location": "L85", "receiver": null}, {"caller_nid": "scraper_main_main", "callee": "execute", "is_member_call": true, "source_file": "C:\\tt-ai-stack\\01_projects\\makeover-talent-agency\\services\\market-scout\\scraper\\main.py", "source_location": "L96", "receiver": null}, {"caller_nid": "scraper_main_main", "callee": "select", "is_member_call": true, "source_file": "C:\\tt-ai-stack\\01_projects\\makeover-talent-agency\\services\\market-scout\\scraper\\main.py", "source_location": "L96", "receiver": null}, {"caller_nid": "scraper_main_main", "callee": "table", "is_member_call": true, "source_file": "C:\\tt-ai-stack\\01_projects\\makeover-talent-agency\\services\\market-scout\\scraper\\main.py", "source_location": "L96", "receiver": "client"}, {"caller_nid": "scraper_main_main", "callee": "execute", "is_member_call": true, "source_file": "C:\\tt-ai-stack\\01_projects\\makeover-talent-agency\\services\\market-scout\\scraper\\main.py", "source_location": "L99", "receiver": null}, {"caller_nid": "scraper_main_main", "callee": "in_", "is_member_call": true, "source_file": "C:\\tt-ai-stack\\01_projects\\makeover-talent-agency\\services\\market-scout\\scraper\\main.py", "source_location": "L99", "receiver": null}, {"caller_nid": "scraper_main_main", "callee": "select", "is_member_call": true, "source_file": "C:\\tt-ai-stack\\01_projects\\makeover-talent-agency\\services\\market-scout\\scraper\\main.py", "source_location": "L99", "receiver": null}, {"caller_nid": "scraper_main_main", "callee": "table", "is_member_call": true, "source_file": "C:\\tt-ai-stack\\01_projects\\makeover-talent-agency\\services\\market-scout\\scraper\\main.py", "source_location": "L99", "receiver": "client"}, {"caller_nid": "scraper_main_main", "callee": "get", "is_member_call": true, "source_file": "C:\\tt-ai-stack\\01_projects\\makeover-talent-agency\\services\\market-scout\\scraper\\main.py", "source_location": "L104", "receiver": "a"}, {"caller_nid": "scraper_main_main", "callee": "get", "is_member_call": true, "source_file": "C:\\tt-ai-stack\\01_projects\\makeover-talent-agency\\services\\market-scout\\scraper\\main.py", "source_location": "L104", "receiver": null}, {"caller_nid": "scraper_main_main", "callee": "get", "is_member_call": true, "source_file": "C:\\tt-ai-stack\\01_projects\\makeover-talent-agency\\services\\market-scout\\scraper\\main.py", "source_location": "L109", "receiver": "item"}, {"caller_nid": "scraper_main_main", "callee": "get", "is_member_call": true, "source_file": "C:\\tt-ai-stack\\01_projects\\makeover-talent-agency\\services\\market-scout\\scraper\\main.py", "source_location": "L110", "receiver": "item"}, {"caller_nid": "scraper_main_main", "callee": "items", "is_member_call": true, "source_file": "C:\\tt-ai-stack\\01_projects\\makeover-talent-agency\\services\\market-scout\\scraper\\main.py", "source_location": "L113", "receiver": "latest_assessments"}, {"caller_nid": "scraper_main_main", "callee": "get", "is_member_call": true, "source_file": "C:\\tt-ai-stack\\01_projects\\makeover-talent-agency\\services\\market-scout\\scraper\\main.py", "source_location": "L114", "receiver": "assessment"}, {"caller_nid": "scraper_main_main", "callee": "lower", "is_member_call": true, "source_file": "C:\\tt-ai-stack\\01_projects\\makeover-talent-agency\\services\\market-scout\\scraper\\main.py", "source_location": "L117", "receiver": "kw"}, {"caller_nid": "scraper_main_main", "callee": "lower", "is_member_call": true, "source_file": "C:\\tt-ai-stack\\01_projects\\makeover-talent-agency\\services\\market-scout\\scraper\\main.py", "source_location": "L117", "receiver": "title"}, {"caller_nid": "scraper_main_main", "callee": "append", "is_member_call": true, "source_file": "C:\\tt-ai-stack\\01_projects\\makeover-talent-agency\\services\\market-scout\\scraper\\main.py", "source_location": "L118", "receiver": "new_alerts"}, {"caller_nid": "scraper_main_main", "callee": "get", "is_member_call": true, "source_file": "C:\\tt-ai-stack\\01_projects\\makeover-talent-agency\\services\\market-scout\\scraper\\main.py", "source_location": "L121", "receiver": "item"}, {"caller_nid": "scraper_main_main", "callee": "execute", "is_member_call": true, "source_file": "C:\\tt-ai-stack\\01_projects\\makeover-talent-agency\\services\\market-scout\\scraper\\main.py", "source_location": "L126", "receiver": null}, {"caller_nid": "scraper_main_main", "callee": "insert", "is_member_call": true, "source_file": "C:\\tt-ai-stack\\01_projects\\makeover-talent-agency\\services\\market-scout\\scraper\\main.py", "source_location": "L126", "receiver": null}, {"caller_nid": "scraper_main_main", "callee": "table", "is_member_call": true, "source_file": "C:\\tt-ai-stack\\01_projects\\makeover-talent-agency\\services\\market-scout\\scraper\\main.py", "source_location": "L126", "receiver": "client"}]}